{"name":"build-javascript","namedChunkGroups":{"polyfill":{"name":"polyfill","assets":[{"name":"webpack-runtime-ad637fa42a751fd0ee6f.js","size":5322},{"name":"polyfill-ece92e383fb62608509a.js","size":85838}],"filteredAssets":0,"assetsSize":91160,"filteredAuxiliaryAssets":2,"auxiliaryAssetsSize":228438},"app":{"name":"app","assets":[{"name":"webpack-runtime-ad637fa42a751fd0ee6f.js","size":5322},{"name":"framework-3968e0c6767cac35e9b3.js","size":128706},{"name":"app-874be0f8e559f8bc206b.js","size":55829}],"filteredAssets":0,"assetsSize":189857,"filteredAuxiliaryAssets":3,"auxiliaryAssetsSize":563300},"component---src-pages-404-jsx":{"name":"component---src-pages-404-jsx","assets":[{"name":"styles.c8298ee07ec1dc545fda.css","size":160808},{"name":"commons-6a63099032260511019f.js","size":16392},{"name":"component---src-pages-404-jsx-266efe969171c1fcba9b.js","size":568}],"filteredAssets":0,"assetsSize":177768,"filteredAuxiliaryAssets":2,"auxiliaryAssetsSize":68825},"component---src-pages-index-jsx":{"name":"component---src-pages-index-jsx","assets":[{"name":"styles.c8298ee07ec1dc545fda.css","size":160808},{"name":"b452aa78-da5bafa25fab60bf3d99.js","size":14319662},{"name":"e73e9428-5ed53f686eb68c93c589.js","size":429599},{"name":"2c796e83-9eb77a05c844363d4295.js","size":763780},{"name":"commons-6a63099032260511019f.js","size":16392},{"name":"component---src-pages-index-jsx-669b9040012ad9c176a9.js","size":238334}],"filteredAssets":0,"assetsSize":15928575,"filteredAuxiliaryAssets":5,"auxiliaryAssetsSize":18556869}},"assetsByChunkName":{"polyfill":["webpack-runtime-ad637fa42a751fd0ee6f.js","polyfill-ece92e383fb62608509a.js"],"app":["webpack-runtime-ad637fa42a751fd0ee6f.js","framework-3968e0c6767cac35e9b3.js","app-874be0f8e559f8bc206b.js"],"component---src-pages-404-jsx":["styles.c8298ee07ec1dc545fda.css","commons-6a63099032260511019f.js","component---src-pages-404-jsx-266efe969171c1fcba9b.js"],"component---src-pages-index-jsx":["styles.c8298ee07ec1dc545fda.css","b452aa78-da5bafa25fab60bf3d99.js","e73e9428-5ed53f686eb68c93c589.js","2c796e83-9eb77a05c844363d4295.js","commons-6a63099032260511019f.js","component---src-pages-index-jsx-669b9040012ad9c176a9.js"]},"childAssetsByChunkName":{}}